batchfactory/__init__.py
batchfactory/__main__.py
batchfactory/brokers/__init__.py
batchfactory/brokers/concurrent_api_call_broker.py
batchfactory/brokers/llm_broker.py
batchfactory/brokers/llm_embedding_broker.py
batchfactory/core/__init__.py
batchfactory/core/base_op.py
batchfactory/core/broker.py
batchfactory/core/entry.py
batchfactory/core/executor.py
batchfactory/core/ledger.py
batchfactory/core/op_graph.py
batchfactory/core/project_folder.py
batchfactory/lib/__init__.py
batchfactory/lib/base64_utils.py
batchfactory/lib/llm_backend.py
batchfactory/lib/markdown_utils.py
batchfactory/lib/model_list.py
batchfactory/lib/prompt_maker.py
batchfactory/lib/utils.py
batchfactory/lib/version_utils.py
batchfactory/op/__init__.py
batchfactory/op/_registery.py
batchfactory/op/broker_op.py
batchfactory/op/checkpoint_op.py
batchfactory/op/common_op.py
batchfactory/op/control_flow_op.py
batchfactory/op/io_op.py
batchfactory/op/llm_dialogue_op.py
batchfactory/op/llm_embedding_op.py
batchfactory/op/llm_op.py
batchfactory/op/functional/__init__.py
batchfactory/op/functional/llm_strings.py
batchfactory/op/functional/text_chunking.py
batchfactory-0.6.2.dist-info/METADATA
batchfactory-0.6.2.dist-info/WHEEL
batchfactory-0.6.2.dist-info/licenses/LICENSE
batchfactory-0.6.2.dist-info/RECORD
