Metadata-Version: 2.4
Name: batchfactory
Version: 0.6.2
Summary: Composable, cache-aware batch processing pipelines for LLMs, APIs, and dataset generation.
Project-URL: Homepage, https://github.com/fangzhangmnm/batchfactory
Project-URL: Issues, https://github.com/fangzhangmnm/batchfactory/issues
Author-email: fangzhangmnm <1561797062@qq.com>
License-Expression: MIT
License-File: LICENSE
Classifier: Operating System :: OS Independent
Classifier: Programming Language :: Python :: 3
Requires-Python: >=3.9
Requires-Dist: aiofiles
Requires-Dist: aiolimiter
Requires-Dist: jsonlines
Requires-Dist: msgpack
Requires-Dist: nest-asyncio
Requires-Dist: numpy
Requires-Dist: openai
Requires-Dist: pyarrow
Requires-Dist: pydantic
Requires-Dist: pytest
Requires-Dist: tqdm
